invoices.py
mindpowered_invoices/Invoices.py
mindpowered_invoices/__init__.py
mindpowered_invoices-0.0.5.dist-info/LICENSE.txt
mindpowered_invoices-0.0.5.dist-info/METADATA
mindpowered_invoices-0.0.5.dist-info/WHEEL
mindpowered_invoices-0.0.5.dist-info/top_level.txt
mindpowered_invoices-0.0.5.dist-info/RECORD
